LICENSE
MANIFEST.in
README.md
cryptotool
setup.py
cryptos/__init__.py
cryptos/blocks.py
cryptos/composite.py
cryptos/constants.py
cryptos/deterministic.py
cryptos/english.txt
cryptos/keystore.py
cryptos/main.py
cryptos/mnemonic.py
cryptos/py2specials.py
cryptos/py3specials.py
cryptos/ripemd.py
cryptos/segwit_addr.py
cryptos/stealth.py
cryptos/transaction.py
cryptos/wallet.py
cryptos/wallet_utils.py
cryptos/coins/__init__.py
cryptos/coins/base.py
cryptos/coins/bitcoin.py
cryptos/coins/bitcoin_cash.py
cryptos/coins/bitcoin_gold.py
cryptos/coins/dash.py
cryptos/coins/dogecoin.py
cryptos/coins/litecoin.py
cryptos/coins/waykicoin.py
cryptos/electrumx_client/__init__.py
cryptos/electrumx_client/jsonrpc.py
cryptos/electrumx_client/rpc.py
cryptos/electrumx_client/test.py
cryptos/electrumx_client/util.py
cryptos/explorers/__init__.py
cryptos/explorers/base_insight.py
cryptos/explorers/bitpay.py
cryptos/explorers/blockchain.py
cryptos/explorers/blockcypher.py
cryptos/explorers/blockdozer.py
cryptos/explorers/btg_explorer.py
cryptos/explorers/dash_siampm.py
cryptos/explorers/sochain.py
cryptos/explorers/utils.py
pycointools.egg-info/PKG-INFO
pycointools.egg-info/SOURCES.txt
pycointools.egg-info/dependency_links.txt
pycointools.egg-info/top_level.txt