Metadata-Version: 2.1
Name: pycointools
Version: 0.0.1
Summary: Python Crypto Coin Tools
Home-page: http://github.com/primal100/pybitcointools
Author: Paul Martin
Author-email: paulmartinforwork@gmail.com
License: UNKNOWN
Platform: UNKNOWN
Classifier: Programming Language :: Python :: 3
Classifier: License :: OSI Approved :: MIT License
Classifier: Operating System :: OS Independent
